stark_utilities/__init__.py
stark_utilities/utilities.py
stark_utilities-0.0.5.dist-info/LICENCE.txt
stark_utilities-0.0.5.dist-info/METADATA
stark_utilities-0.0.5.dist-info/WHEEL
stark_utilities-0.0.5.dist-info/top_level.txt
stark_utilities-0.0.5.dist-info/RECORD
