Metadata-Version: 2.1
Name: stark-utilities
Version: 0.0.5
Summary: Stark utilities
Home-page: UNKNOWN
Author: Stark Digital Media Services Pvt. Ltd.
Author-email: starkengg81@gmail.com
License: UNKNOWN
Keywords: stark,utilities,stark-utilities,stark_utilities
Platform: UNKNOWN
Classifier: Operating System :: OS Independent
Classifier: License :: OSI Approved :: MIT License
Classifier: Programming Language :: Python :: 3
Requires-Python: >=3.6
